{
    "type":"object",
    "required":false,
    "javaType":"com.lukaspradel.steamapi.data.json.packagedetails.Packagedetails",
    "additionalProperties":{
        "type":"object",
        "required":false,
        "javaType":"com.lukaspradel.steamapi.data.json.packagedetails.Packagedetail",
        "properties":{
            "data":{
                "type":"object",
                "required":false,
                "properties":{
                    "apps":{
                        "type":"array",
                        "required":false,
                        "items":{
                            "type":"object",
                            "required":false,
                            "properties":{
                                "id":{
                                    "type":"number",
                                    "required":false
                                },
                                "name":{
                                    "type":"string",
                                    "required":false
                                }
                            }
                        }
                    },
                    "controller":{
                        "type":"object",
                        "required":false,
                        "properties":{
                            "full_gamepad":{
                                "type":"boolean",
                                "id":"http://jsonschema.net/123/data/controller/full_gamepad",
                                "required":false
                            }
                        }
                    },
                    "name":{
                        "type":"string",
                        "required":false
                    },
                    "page_image":{
                        "type":"string",
                        "required":false
                    },
                    "platforms":{
                        "type":"object",
                        "required":false,
                        "properties":{
                            "linux":{
                                "type":"boolean",
                                "required":false
                            },
                            "mac":{
                                "type":"boolean",
                                "required":false
                            },
                            "windows":{
                                "type":"boolean",
                                "required":false
                            }
                        }
                    },
                    "price":{
                        "type":"object",
                        "required":false,
                        "properties":{
                            "currency":{
                                "type":"string",
                                "required":false
                            },
                            "discount_percent":{
                                "type":"number",
                                "required":false
                            },
                            "final":{
                                "type":"number",
                                "required":false
                            },
                            "individual":{
                                "type":"number",
                                "required":false
                            },
                            "initial":{
                                "type":"number",
                                "required":false
                            }
                        }
                    },
                    "release_date":{
                        "type":"object",
                        "required":false,
                        "properties":{
                            "coming_soon":{
                                "type":"boolean",
                                "required":false
                            },
                            "date":{
                                "type":"string",
                                "required":false
                            }
                        }
                    },
                    "small_logo":{
                        "type":"string",
                        "required":false
                    }
                }
            },
            "success":{
                "type":"boolean",
                "required":false
            }
        }
    }
}